LICENSE
MANIFEST.in
README.rst
pyproject.toml
setup.cfg
setup.py
django_ranks/__init__.py
django_ranks/admin.py
django_ranks/apps.py
django_ranks/base.py
django_ranks/models.py
django_ranks/test_models.py
django_ranks/tests.py
django_ranks/views.py
django_ranks.egg-info/PKG-INFO
django_ranks.egg-info/SOURCES.txt
django_ranks.egg-info/dependency_links.txt
django_ranks.egg-info/requires.txt
django_ranks.egg-info/top_level.txt
django_ranks/migrations/__init__.py